djwkhtmltopdf/url_helper.py
djwkhtmltopdf/utils.py
djwkhtmltopdf/models.py
djwkhtmltopdf/forms.py
djwkhtmltopdf/test_settings.py
djwkhtmltopdf/admin.py
djwkhtmltopdf/__init__.py
djwkhtmltopdf/tests/urls.py
djwkhtmltopdf/tests/run.py
djwkhtmltopdf/tests/views.py
djwkhtmltopdf/tests/tests.py
djwkhtmltopdf/tests/__init__.py
djwkhtmltopdf/fixtures/initial.json
dj_wkhtmltopdf-1.0.2.dist-info/RECORD
dj_wkhtmltopdf-1.0.2.dist-info/WHEEL
dj_wkhtmltopdf-1.0.2.dist-info/METADATA
dj_wkhtmltopdf-1.0.2.dist-info/DESCRIPTION.rst
dj_wkhtmltopdf-1.0.2.dist-info/top_level.txt
dj_wkhtmltopdf-1.0.2.dist-info/metadata.json
